AUTHORS
CHANGELOG.txt
DESCRIPTION
LICENSE
MANIFEST.in
README.rst
setup.cfg
setup.py
tox.ini
db_obcuscate_id.egg-info/PKG-INFO
db_obcuscate_id.egg-info/SOURCES.txt
db_obcuscate_id.egg-info/dependency_links.txt
db_obcuscate_id.egg-info/requires.txt
db_obcuscate_id.egg-info/top_level.txt
db_obfuscate/.DS_Store
db_obfuscate/__init__.py
db_obfuscate/admin.py
db_obfuscate/management/.DS_Store
db_obfuscate/management/__init__.py
db_obfuscate/management/commands/.DS_Store
db_obfuscate/management/commands/__init__.py
db_obfuscate/management/commands/db.py
db_obfuscate/scripts/.DS_Store
db_obfuscate/scripts/raw_sql/.DS_Store
db_obfuscate/scripts/raw_sql/add_model_encryption.SQL
db_obfuscate/tests/.coveragerc
db_obfuscate/tests/__init__.py
db_obfuscate/tests/factories.py
db_obfuscate/tests/models_tests.py
db_obfuscate/tests/runtests.py
db_obfuscate/tests/south_settings.py
db_obfuscate/tests/test_settings.py
db_obfuscate/tests/urls.py
db_obfuscate/tests/test_app/__init__.py
db_obfuscate/tests/test_app/models.py
db_obfuscate/tests/test_app/templates/400.html
db_obfuscate/tests/test_app/templates/500.html