Metadata-Version: 1.0
Name: db-obcuscate-id
Version: 0.1
Summary: A reusable Django app that psuedo encrypts your id from a database level.
